flask_utils/__init__.py
flask_utils/celery/__init__.py
flask_utils/config/__init__.py
flask_utils/deployment_release/__init__.py
flask_utils/pagination/__init__.py
flask_utils/restful/__init__.py
flask_utils/sentry/__init__.py
flask_utils/testing/__init__.py
flask_utils/token_auth/ShortlivedTokenMixin.py
flask_utils/token_auth/__init__.py
flask_utils/token_auth/decorators.py
flask_utils/webargs/__init__.py
nickw_flask_utils-1.2.4.dist-info/LICENSE
nickw_flask_utils-1.2.4.dist-info/METADATA
nickw_flask_utils-1.2.4.dist-info/WHEEL
nickw_flask_utils-1.2.4.dist-info/top_level.txt
nickw_flask_utils-1.2.4.dist-info/RECORD
