Metadata-Version: 2.1
Name: nickw-flask-utils
Version: 1.2.4
Summary: A set of utilities to make working with flask web applications easier.
Home-page: https://github.com/nickw444/nickw-flask-utils
Author: Nick Whyte
Author-email: nick@nickwhyte.com
License: UNKNOWN
Platform: UNKNOWN
Requires-Python: >=3.4
License-File: LICENSE
Provides-Extra: celery
Requires-Dist: celery ; extra == 'celery'
Provides-Extra: ldap
Provides-Extra: pagination
Requires-Dist: webargs ; extra == 'pagination'
Requires-Dist: marshmallow ; extra == 'pagination'
Provides-Extra: restful
Requires-Dist: flask-restful ; extra == 'restful'
Provides-Extra: sentry
Requires-Dist: raven[flask] ; extra == 'sentry'
Provides-Extra: token_auth
Requires-Dist: marshmallow ; extra == 'token_auth'
Provides-Extra: webargs
Requires-Dist: webargs ; extra == 'webargs'
